wbpFilebrowser/__init__.py
wbpFilebrowser/dirtreewindow.py
wbpFilebrowser-0.2.1.dist-info/LICENSE
wbpFilebrowser-0.2.1.dist-info/METADATA
wbpFilebrowser-0.2.1.dist-info/WHEEL
wbpFilebrowser-0.2.1.dist-info/entry_points.txt
wbpFilebrowser-0.2.1.dist-info/top_level.txt
wbpFilebrowser-0.2.1.dist-info/RECORD
